.gitignore
MANIFEST.in
README.rst
README.txt
setup.cfg
setup.py
collective/__init__.py
collective.multilanguagefields.egg-info/PKG-INFO
collective.multilanguagefields.egg-info/SOURCES.txt
collective.multilanguagefields.egg-info/dependency_links.txt
collective.multilanguagefields.egg-info/entry_points.txt
collective.multilanguagefields.egg-info/namespace_packages.txt
collective.multilanguagefields.egg-info/not-zip-safe
collective.multilanguagefields.egg-info/paster_plugins.txt
collective.multilanguagefields.egg-info/requires.txt
collective.multilanguagefields.egg-info/top_level.txt
collective/multilanguagefields/__init__.py
collective/multilanguagefields/behaviors.py
collective/multilanguagefields/configure.zcml
collective/multilanguagefields/fields.py
collective/multilanguagefields/interfaces.py
collective/multilanguagefields/tests.py
collective/multilanguagefields/utils.py
collective/multilanguagefields/views.py
collective/multilanguagefields/profiles/default/jsregistry.xml
collective/multilanguagefields/profiles/default/metadata.xml
collective/multilanguagefields/resources/README.txt
collective/multilanguagefields/resources/javascripts/main.js
docs/HISTORY.txt
docs/INSTALL.txt
docs/LICENSE.GPL
docs/LICENSE.txt