Metadata-Version: 1.1
Name: collective.multilanguagefields
Version: 0.7
Summary: Multi language fields for Plone
Home-page: http://svn.plone.org/svn/collective/
Author: UNKNOWN
Author-email: UNKNOWN
License: GPL
Platform: UNKNOWN
Classifier: Framework :: Plone
Classifier: Programming Language :: Python
